Workbook

Sheet Guide
D1: A guide to making on-farm tree planting decisions
D5: Background | G5: This section provides background information regarding on-farm tree planting.
D9: Establishment Costs
F10: The costs associated with tree plantations include:
F11: Establishment and maintenance costs for the trees
F12: The opportunity cost of the land that is planted to the trees
F13: Costs to adjacent land that is affected by the trees (see below for more info)
D15: Shelter
F16: Trees can offer valuable shelter to livestock, reducing exposure to harsh weather, lowering energy expenditure, and improving survival rates—particularly for vulnerable animals such as twin-bearing ewes.
F17: The economic benefits of shelter depends on several factors:
F18: Livestock behaviour: Animals do not always seek shelter, so the width and layout of the paddock affect how much protection they receive.
F19: Mob priority and management: Greater benefit is achieved when high-priority mobs (e.g. scanned twin-bearing ewes) are placed in sheltered paddocks. If a farmer does not scan for pregnancy status, shelter is less likely to be targeted where it’s most effective.
F20: Paddock configuration: Narrower or well-oriented paddocks provide better access to tree shelter across the mob.
D22: Adjacent pasture and crop production
F23: Tree belts can influence pasture and crop yields through two competing effects:
F24: Reduced yield near trees due to shading and competition for water and nutrients. Production is reduced by 48% between 2 and 11.2m from the trees.
F25: Increased yield beyond the competition zone due to protection from wind, which reduces plant stress and evaporation. Yield is increased 4% between 16 and 80m from trees.
D27: Carbon sequestration
F28: Planting trees is a method of carbon sequestration. Projects registered under the ACCU Scheme can generate tradable carbon credits (ACCUs). Once generated, you have three management options:
F29: You can sell them, providing an additional revenue stream for your farm and a return on investment.
F30: You can hold them as a future asset.
F31: You can inset them into your farm, meaning that you are using self-generated ACCUs to reduce your farm’s emissions.
F32: Establishing a carbon project incurs costs for monitoring, administration and compliance.
D34: Biodiversity
F35: Tree plantations, particularly those using native species, can significantly enhance on-farm biodiversity. Emerging environmental markets now offer financial incentives and potential income streams for projects that deliver these biodiversity benefits.
F36: The number of credits and the sale price varies a lot by vegetation type and local demand, but past data shows that sites yield often falls around 4–8 credits per hectare and recent sales suggest prices commonly in the order of $2,300–$8,500 per credit
F37: Establishing a carbon project incurs costs for monitoring, administration and compliance.
D39: Biomass production
F40: Above-ground biomass can be harvested and sold to produce clean energy and biofuels, such as diesel, through processes like pyrolysis.
F41: Costs include harvesting, on-farm transport and road transport to the bioenergy plant.
D43: Micro-climate
F44: At the farm scale, trees primarily influence the microclimate through evapotranspiration, which increases local humidity and slightly moderates temperature, and may also contribute to small, localised increases in rainfall
F45: DPIRD is currently undertaking a trial to further investigate the interaction between tree cover and microclimate changes.
F46: It is expected that a substantial area of tree establishment would be required before any measurable microclimate effects translate into on-farm production gains.
D48: Groundwater discharge and salinity
F49: Dryland salinity continues to challenge WA farms, reducing yield and rendering land unproductive. Deep-rooted vegetation draws water from deeper in the soil profile, helping to lower the water table and prevent saline groundwater from rising.
F50: Plantings need to be strategically located, typically targeting recharge areas and valley floors, to maximise their impact on reducing salinity.
F51: Research indicates that substantial revegetation—potentially up to 50% of the catchment—may be required to effectively halt the spread of salinity.
D53: Erosion
F54: Australian soils are prone to erosion, which strips away valuable topsoil and nutrients. Vegetation helps stabilise the soil with their root systems, while their canopies reduce wind and water impact.
F55: The economic implications of erosion control are highly farm-specific. The extent of any benefit depends on local climate, soil type, and the practices already in place to manage it.
F56: Most farms have adopted effective erosion-mitigating measures—such as minimum tillage and stubble retention—so establishing additional trees often provides limited direct financial return.
F57: However, tree establishment may still offer economic benefits where it allow intensification. For example, well-placed shelterbelts could enable farmers to graze paddocks more intensively.
D62: Economics | G62: This section quantifies the economics of various tree plantation scenarios.
F66: Definitions
G68: Tree belt (or block):
G69: The tree belt refers to the area occupied by planted trees, including an adjacent side buffer. The side buffer is a no-cropping zone immediately next to the trees
G70: where agricultural production is negligible or uneconomic, and therefore excluded from active use.
G71: In this analysis, the side buffer (no-crop zone) is 4m wide.
G73: Competition zone:
G74: The competition zone is the adjacent area that remains cropped or grazed under normal management. However, productivity in this zone may be influenced by the presence
G75: of trees through positive (e.g. shelter, microclimate moderation) and/or negative (e.g. competition for water, nutrients, and light) interactions.
G76: #VALUE!
F94: Assumptions (adjustable cells in orange)
F95: Cost | O95: Defaults
F97: Category | G97: Cost Item | H97: Cost Value | I97: Unit
F98: Initial Costs - Site Prep | G98: Ripping/Mounding | H98: 280 | I98: $/ha | O98: 280
G99: Initial Weed Control | H99: 54 | I99: $/ha | O99: 54
G100: Fertiliser (Base) | H100: 0 | I100: $/ha | O100: 0
G101: Fertiliser (Extra if Harvested) | H101: 0 | I101: $/ha | O101: 0
F102: Initial Costs - Planting | G102: Seedlings | H102: 0.8 | I102: $/plant | O102: 0.8
G103: Mortality | H103: 0.1 | I103: % | O103: 0.1
G104: Planting Rate | H104: 3000 | I104: plants/day | O104: 3000
G105: Planting Equipment | H105: 300 | I105: $/day | O105: 300
G106: Farmer Labour (Planting) | H106: 800 | I106: $/day | O106: 800
F107: Year 1 Costs | G107: Weed Control | H107: 10 | I107: $/ha | O107: 10
G108: Fertiliser (Base) | H108: 0 | I108: $/ha | O108: 0
G109: Fertiliser (Extra if Harvested) | H109: 0 | I109: $/ha | O109: 0
F110: Ongoing Costs | G110: Weed Control | H110: 0 | I110: $/ha | O110: 0
G111: Fertiliser (Base) | H111: 0 | I111: $/ha | O111: 0
G112: Fertiliser (Extra if Harvested) | H112: 0 | I112: $/ha | O112: 0
F113: Sequestration Costs | G113: Setup of sequestration monitoring & auditing | H113: 10000 | I113: $/farm | O113: 10000
G114: Annual monitoring & auditing of sequestration | H114: 25 | I114: $/ha | O114: 25
F115: Biodiversity Cost | G115: Setup of biodiversity monitoring & auditing | H115: 10000 | I115: $/farm | O115: 10000
G116: Annual monitoring & auditing of biodiversity | H116: 25 | I116: $/ha | O116: 25
F117: Harvesting Costs | G117: Contract Cost | H117: 300 | I117: $/hr | O117: 300
G118: Harvest Rate | H118: 40 | I118: t/hr | O118: 40
G119: Transport | H119: 0.15 | I119: $/t/km
G120: Transport Distance | H120: 60 | I120: km | O120: 0.15
F123: Shelter
F143: Adjacent pasture and crop production - competition zone
G145: From 0–7.2m, the average yield in this zone is estimated at 62.5% of open yield.
G146: A 4% yield increase from wind protection between 4-20H (16-80m).
F164: Cabon sequestration
H166: Carb Block | I166: Carb Belt | J166: Bio Block | K166: Harv Belt
G167: Average yield (green t/ha/yr) | H167: 7.43 | I167: 10.4 | J167: 4.14 | K167: 4.04 | O167: 7.43 | P167: 10.4 | Q167: 4.14 | R167: 4.04
H169: Low (-50%) | I169: Standard | J169: High (+50%)
G170: Carbon price ($/t co2e) | H170: =I170*0.5 -> 20 | I170: 40 | J170: =I170*1.5 -> 60 | O170: 20 | P170: 40 | Q170: 60
F192: Biodiversity
H194: Carb Block | I194: Carb Belt | J194: Bio Block | K194: Harv Belt
G195: Biodiversity value ($/ha) | H195: 17000 | I195: 8500 | J195: 22500 | K195: 4500 | O195: 17000 | P195: 8500 | Q195: 22500 | R195: 4500
F198: Biomass Harvesting
H200: Carb Block | I200: Carb Belt | J200: Bio Block | K200: Harv Belt | O200: 0 | P200: 0 | Q200: 0 | R200: 7.0277679
G201: Average yield (green t/ha/yr) | H201: 0 | I201: 0 | J201: 0 | K201: 7.0277679
H203: Low (-50%) | I203: Standard | J203: High (+50%)
G204: Biomass price ($/t green) | H204: =I204*0.5 -> 25 | I204: 50 | J204: =I204*1.5 -> 75 | O204: 25 | P204: 50 | Q204: 75
F207: Micro-climate
G209: To estimate potential rainfall changes from revegetation, a 10 km rainfall footprint radius was applied to
G210: represent the local area influenced by vegetation.
G211: Within this footprint, a 15% increase in tree cover was assumed to increase rainfall by 2.6% (Syktus & McAlpine, 2016).
...

Sheet Database
A1: Output
B4: Component option | C4: Profit ($/ha of trees)
A5: control | C5: =B24 -> 311234 | E5: =C5 -> 311234
A6: Land opportunity cost | C6: =SUMIFS($F$29:$F$40,$A$29:$A$40,Guide!G245,$B$29:$B$40,Guide!G247,$C$29:$C$40,Guide!G248) -> 169 | E6: =C6 -> 169
A7: +trees | B7: 1 | C7: =Calculations!B19 -> 116.34927 | E7: =C7 -> 116.34927
A8: +livestock shelter | B8: 2 | C8: =SUMIFS($E$70:$E$117,Database!$A$70:$A$117,Guide!$G$245,$B$70:$B$117,Guide!$G$246,$C$70:$C$117,Guide!$G$247,$D$70:$D$117,Guide!$G$248) -> 2 | E8: =C8 -> 2
A9: +adj pad interaction | B9: 3 | C9: =SUMIFS($D$121:$D$136,$A$121:$A$136,Guide!$G$245,$B$121:$B$136,Guide!$G$246,$C$121:$C$136,Guide!$G$247) -> -188.63158 | E9: =C9 -> -188.63158
A10: +carbon | B10: 4 | C10: =Calculations!B54 -> 212.53227 | E10: =C10 -> 212.53227
A11: +biodiversity | B11: 5 | C11: =Calculations!B124 -> -415.23852 | E11: =C11 -> -415.23852
A12: +harvesting | B12: 6 | C12: =Calculations!$B$154 -> 192.88585 | E12: =C12 -> 192.88585
A13: +micro-climate | C13: - | D13: - | E13: =SUMIFS($D$50:$D$51,$A$50:$A$51,Guide!$G$245) -> 8.9025412
A14: +increased grazing | C14: - | D14: - | E14: =SUMIFS($C$59:$C$66,$A$59:$A$66,Guide!$G$245,$B$59:$B$66,Guide!$G$246) -> 4.27054
A15: +reduced salinity spread | C15: =SUMIFS($C$44:$C$45,$A$44:$A$45,Guide!$G$245) -> -3444 | E15: =-C15*E18/Guide!$G$248 -> 3444
D17: Reduction in recharge
A18: Recharge (mm) | B18: 6 | C18: =SUMIFS(INDEX($M$143:$N$4031,0,MATCH(Guide!$G$245,Scenarios!$A$2:$A$3,0)),$B$143:$B$4031,Guide!$G$246,$C$143:$C$4031,Guide!$G$247,$D$143:$D$4031,Guide!$G$248,$E$143:$E$4031,Guide!$J$245,$F$143:$F$4031,Guide!$J$246,$G$143:$G$4031,Guide!$J$247,$H$143:$H$4031,B18) -> 0 | D18: =VLOOKUP(Guide!G245,$A$24:$C$25,3)-C18 -> 16.137 | E18: =D18/VLOOKUP(Guide!G245,$A$24:$C$25,3) -> 1
A22: Control
A23: Location | B23: Farm Profit | C23: Groundwater Recharge (mm)
A24: Central wheatbelt | B24: 311234 | C24: 16.137
A25: Eastern wheatbelt | B25: 299026 | C25: 12.331
A27: Land opp cost
A28: Location | B28: Soil | C28: Area | D28: Farm Profit | E28: Opp cost | F28: Opp cost ($/ha)
A29: Central wheatbelt | B29: Poor | C29: 1 | D29: 311145 | E29: 89 | F29: 89
A30: Central wheatbelt | B30: Poor | C30: 10 | D30: 310336 | E30: 898 | F30: 89.8
A31: Central wheatbelt | B31: Poor | C31: 100 | D31: 301364 | E31: 9870 | F31: 98.7
A32: Central wheatbelt | B32: Good | C32: 1 | D32: 311065 | E32: 169 | F32: 169
A33: Central wheatbelt | B33: Good | C33: 10 | D33: 309537 | E33: 1697 | F33: 169.7
A34: Central wheatbelt | B34: Good | C34: 100 | D34: 294094 | E34: 17140 | F34: 171.4
A35: Eastern wheatbelt | B35: Poor | C35: 1 | D35: 299003 | E35: 23 | F35: 23
A36: Eastern wheatbelt | B36: Poor | C36: 10 | D36: 298796 | E36: 230 | F36: 23
A37: Eastern wheatbelt | B37: Poor | C37: 100 | D37: 296722 | E37: 2304 | F37: 23.04
A38: Eastern wheatbelt | B38: Good | C38: 1 | D38: 298867 | E38: 159 | F38: 159
A39: Eastern wheatbelt | B39: Good | C39: 10 | D39: 297438 | E39: 1588 | F39: 158.8
A40: Eastern wheatbelt | B40: Good | C40: 100 | D40: 282976 | E40: 16050 | F40: 160.5
A42: Salinity spread
A43: Location | B43: Farm Profit | C43: Cost of salinity spread
A44: Central wheatbelt | B44: 307790 | C44: -3444
A45: Eastern wheatbelt | B45: 295088 | C45: -3938
A48: Micro-climate
A49: Location | B49: Farm Profit | C49: Farm Profit Increase | D49: Profit ($/ha of trees)
A50: Central wheatbelt | B50: 353185 | C50: 41951 | D50: 8.9025412
A51: Eastern wheatbelt | B51: 419402 | C51: 120376 | D51: 25.545334
A53: Footprint area (ha) | B53: 10 | C53: 31415
A54: Area of trees required to increase rainfall by 2.6% | B54: 4712.25
A57: Erosion limit
A58: Location | B58: Scenario | C58: profit ($/ha of tree)
A59: Central wheatbelt | B59: Carb Block | C59: 0
A60: Central wheatbelt | B60: Carb Belt | C60: 10.67635
A61: Central wheatbelt | B61: Bio Block | C61: 0
A62: Central wheatbelt | B62: Harv Belt | C62: 4.27054
A63: Eastern wheatbelt | B63: Carb Block | C63: 0
A64: Eastern wheatbelt | B64: Carb Belt | C64: 27.242902
A65: Eastern wheatbelt | B65: Bio Block | C65: 0
A66: Eastern wheatbelt | B66: Harv Belt | C66: 10.897161
A68: Shelter
A69: Location | B69: Scenario | C69: Soil | D69: Area | E69: shelter benefits ($/ha)
A70: Central wheatbelt | B70: Carb Block | C70: Poor | D70: 1 | E70: 1
A71: Central wheatbelt | B71: Carb Block | C71: Poor | D71: 10 | E71: 1.1
A72: Central wheatbelt | B72: Carb Block | C72: Poor | D72: 100 | E72: 1.06
A73: Central wheatbelt | B73: Carb Block | C73: Good | D73: 1 | E73: 1
A74: Central wheatbelt | B74: Carb Block | C74: Good | D74: 10 | E74: 1.1
A75: Central wheatbelt | B75: Carb Block | C75: Good | D75: 100 | E75: 1.1
A76: Eastern wheatbelt | B76: Carb Block | C76: Poor | D76: 1 | E76: 0
A77: Eastern wheatbelt | B77: Carb Block | C77: Poor | D77: 10 | E77: 0.3
A78: Eastern wheatbelt | B78: Carb Block | C78: Poor | D78: 100 | E78: 0.38
A79: Eastern wheatbelt | B79: Carb Block | C79: Good | D79: 1 | E79: 0
A80: Eastern wheatbelt | B80: Carb Block | C80: Good | D80: 10 | E80: 0.4
A81: Eastern wheatbelt | B81: Carb Block | C81: Good | D81: 100 | E81: 2.59
... A117: Eastern wheatbelt | B117: Harv Belt | C117: Good | D117: 100 | E117: 2.82
A119: Paddock interactions
A120: Location | B120: Scenario | C120: Soil | D120: Interaction benefits ($/ha)
A121: Central wheatbelt | B121: Carb Block | C121: Poor | D121: -13
A122: Central wheatbelt | B122: Carb Block | C122: Good | D122: -37
A123: Eastern wheatbelt | B123: Carb Block | C123: Poor | D123: -20
A124: Eastern wheatbelt | B124: Carb Block | C124: Good | D124: -32
A125: Central wheatbelt | B125: Carb Belt | C125: Poor | D125: -132
A126: Central wheatbelt | B126: Carb Belt | C126: Good | D126: -384
A127: Eastern wheatbelt | B127: Carb Belt | C127: Poor | D127: -210
A128: Eastern wheatbelt | B128: Carb Belt | C128: Good | D128: -337
A129: Central wheatbelt | B129: Bio Block | C129: Poor | D129: -13
A130: Central wheatbelt | B130: Bio Block | C130: Good | D130: -37
A131: Eastern wheatbelt | B131: Bio Block | C131: Poor | D131: -20
A132: Eastern wheatbelt | B132: Bio Block | C132: Good | D132: -32
... A136: Eastern wheatbelt | B136: Harv Belt | C136: Good | D136: -165.22816

Sheet Calculations
A1: Cost
B3: Tree density | C3: Shrub density | F3: Initial Costs - Site Prep | G3: Ripping/Mounding | H3: =Guide!H98 -> 280
A4: Carb Block | B4: 512 | C4: 0 | G4: Initial Weed Control | H4: =Guide!H99 -> 54
A5: Carb Belt | B5: 1000 | C5: 0 | G5: Fertiliser (Base) | H5: =Guide!H100 -> 0
A6: Bio Block | B6: 267 | C6: 300 | G6: Fertiliser (Extra if Harvested) | H6: =Guide!H101 -> 0
A7: Harv Belt | B7: 1000 | C7: 0 | F7: Initial Costs - Planting | G7: Seedlings | H7: =Guide!H102 -> 0.8
G8: Mortality | H8: =Guide!H103 -> 0.1
A9: Planing density | G9: Planting Rate | H9: =Guide!H104 -> 3000
A10: =VLOOKUP(Guide!G246,$A$4:$C$7,2,FALSE)+VLOOKUP(Guide!G246,$A$4:$C$7,3,FALSE) -> 1000 | G10: Planting Equipment | H10: =Guide!H105 -> 300
G11: Farmer Labour (Planting) | H11: =Guide!H106 -> 800
A12: Discount rate | B12: 0.05 | F12: Year 1 Costs | G12: Weed Control | H12: =Guide!H107 -> 10
A13: Project length | B13: 25 | G13: Fertiliser (Base) | H13: =Guide!H108 -> 0
A14: Initial costs (yr 1) | B14: =SUM(H3:H5)+IF(Guide!G246=Calculations!A7,Calculations!H6,0)+A10/(1-H8)*H7+(H10+H11)*((A10/(1-H8))/H9) -> 1630.2963 | G14: Fertiliser (Extra if Harvested) | H14: =Guide!H109 -> 0
A15: Yr2 costs | B15: =SUM(H12:H13)+IF(Guide!G246=Calculations!A7,Calculations!H14,0) -> 10 | F15: Ongoing Costs | G15: Weed Control | H15: =Guide!H110 -> 0
A16: Ongoing costs (>3yr) | B16: =SUM(H15:H16)+IF(Guide!G246=Calculations!A7,H17,0) -> 0 | G16: Fertiliser (Base) | H16: =Guide!H111 -> 0
G17: Fertiliser (Extra if Harvested) | H17: =Guide!H112 -> 0
A18: NPV | B18: {=B14 + B15/(1+$B$12)^1 + SUMPRODUCT(B16/(1+$B$12)^(ROW(INDIRECT("2:"&($B$13-1)))))} -> 1639.8201 | F18: Sequestration Costs | G18: Setup of sequestration monitoring & auditing | H18: =Guide!H113 -> 10000
A19: Annualise the NPV | B19: =B18 * ($B$12 / (1 - (1+$B$12)^-$B$13)) -> 116.34927 | G19: Annual monitoring & auditing of sequestration | H19: =Guide!H114 -> 25
F20: Biodiversity Cost | G20: Setup of biodiversity monitoring & auditing | H20: =Guide!H115 -> 10000
G21: Annual monitoring & auditing of biodiversity | H21: =Guide!H116 -> 25
F22: Harvesting Costs | G22: Contract Cost | H22: =Guide!H117 -> 300
G23: Harvest Rate | H23: =Guide!H118 -> 40
G24: Transport | H24: =Guide!H120 -> 60
A28: Carbon
A29: Risk of reversal buffer | B29: 0.05 | E29: Year | F29: ='[2]Planting config'!$G$13 -> Carbon | G29: ='[2]Planting config'!$H$13 -> Carbon & co-benefits | H29: ='[2]Planting config'!$I$13 -> Biodiversity | I29: ='[2]Planting config'!$J$13 -> Harvested | K29: Year | L29: ='[2]Planting config'!$G$13 -> Carbon | M29: ='[2]Planting config'!$H$13 -> Carbon & co-benefits | N29: ='[2]Planting config'!$I$13 -> Biodiversity | O29: ='[2]Planting config'!$J$13 -> Harvested
A30: Project duration (years) | B30: 25 | E30: 0 | F30: 0 | G30: =F30*1.4 -> 0 | H30: 0 | I30: 0 | K30: 0 | L30: =F30*Guide!H$167/F$56 -> 0 | M30: =G30*Guide!I$167/G$56 -> 0 | N30: =H30*Guide!J$167/H$56 -> 0 | O30: =I30*Guide!K$167/I$56 -> 0
E31: 1 | F31: 904.60832 | G31: 1266.4517 | H31: 901.11027 | I31: 660.31772 | K31: 1 | L31: =F31*Guide!H$167/F$56 -> 905.0906 | M31: =G31*Guide!I$167/G$56 -> 1266.8832 | N31: =H31*Guide!J$167/H$56 -> 900.47885 | O31: =I31*Guide!K$167/I$56 -> 645.13431
A32: Annual monitoring cost ($/ha/yr) | B32: 0 | E32: 2 | F32: 301.17204 | G32: 421.64085 | H32: 67.01672 | I32: 4435.46 | K32: 2 | L32: =F32*Guide!H$167/F$56 -> 301.3326 | M32: =G32*Guide!I$167/G$56 -> 421.78453 | N32: =H32*Guide!J$167/H$56 -> 66.969761 | O32: =I32*Guide!K$167/I$56 -> 4333.4706
A33: Setup cost ($/project) | B33: 0 | E33: 3 | F33: 2044.988 | G33: 2862.9832 | H33: 435.06268 | I33: 13053.774 | K33: 3 | L33: =F33*Guide!H$167/F$56 -> 2046.0783 | M33: =G33*Guide!I$167/G$56 -> 2863.9588 | N33: =H33*Guide!J$167/H$56 -> 434.75782 | O33: =I33*Guide!K$167/I$56 -> 12753.614
A34: Fuel used at t0 | B34: 40 | E34: 4 | F34: 4934.1418 | G34: 6907.7985 | H34: 1463.019 | I34: 17680.035 | K34: 4 | L34: =F34*Guide!H$167/F$56 -> 4936.7723 | M34: =G34*Guide!I$167/G$56 -> 6910.1524 | N34: =H34*Guide!J$167/H$56 -> 1461.9939 | O34: =I34*Guide!K$167/I$56 -> 17273.499
A35: Fuel used in year 1 | B35: 8 | E35: 5 | F35: 7509.7122 | G35: 10513.597 | H35: 2780.338 | I35: 18752.612 | K35: 5 | L35: =F35*Guide!H$167/F$56 -> 7513.7159 | M35: =G35*Guide!I$167/G$56 -> 10517.18 | N35: =H35*Guide!J$167/H$56 -> 2778.3898 | O35: =I35*Guide!K$167/I$56 -> 18321.412
A36: Fuel used in years 2+ | B36: 0 | E36: 6 | F36: 9267.051 | G36: 12973.871 | H36: 3970.4165 | I36: 18198.35 | K36: 6 | L36: =F36*Guide!H$167/F$56 -> 9271.9916 | M36: =G36*Guide!I$167/G$56 -> 12978.292 | N36: =H36*Guide!J$167/H$56 -> 3967.6344 | O36: =I36*Guide!K$167/I$56 -> 17779.895
A37: Fuel CO2 factor (kg CO2e / unit) | B37: 2.7 | E37: 7 | F37: 10283.527 | G37: 14396.938 | H37: 4867.248 | I37: 17043.785 | K37: 7 | L37: =F37*Guide!H$167/F$56 -> 10289.009 | M37: =G37*Guide!I$167/G$56 -> 14401.844 | N37: =H37*Guide!J$167/H$56 -> 4863.8375 | O37: =I37*Guide!K$167/I$56 -> 16651.878
A38: Fuel CH4 factor (kg CO2e / unit) | B38: 0.002123 | E38: 8 | F38: 10762.492 | G38: 15067.488 | H38: 5465.4259 | I38: 15727.245 | K38: 8 | L38: =F38*Guide!H$167/F$56 -> 10768.23 | M38: =G38*Guide!I$167/G$56 -> 15072.623 | N38: =H38*Guide!J$167/H$56 -> 5461.5962 | O38: =I38*Guide!K$167/I$56 -> 15365.611
A39: Fuel N2O factor (kg CO2e / unit) | B39: 0.01351 | E39: 9 | F39: 10882.192 | G39: 15235.069 | H39: 5816.6668 | I39: -46330.213 | K39: 9 | L39: =F39*Guide!H$167/F$56 -> 10887.994 | M39: =G39*Guide!I$167/G$56 -> 15240.261 | N39: =H39*Guide!J$167/H$56 -> 5812.591 | O39: =I39*Guide!K$167/I$56 -> -45264.891
A40: Total fuel factor (kg CO2e / unit) | B40: =SUM(B37:B39) -> 2.715633 | E40: 10 | F40: 10771.241 | G40: 15079.738 | H40: 5981.0237 | I40: 15480.555 | K40: 10 | L40: =F40*Guide!H$167/F$56 -> 10776.984 | M40: =G40*Guide!I$167/G$56 -> 15084.876 | N40: =H40*Guide!J$167/H$56 -> 5976.8328 | O40: =I40*Guide!K$167/I$56 -> 15124.593
A41: Discount rate | B41: =B12 -> 0.05 | E41: 11 | F41: 10516.723 | G41: 14723.413 | H41: 6010.4392 | I41: 15449.357 | K41: 11 | L41: =F41*Guide!H$167/F$56 -> 10522.33 | M41: =G41*Guide!I$167/G$56 -> 14728.43 | N41: =H41*Guide!J$167/H$56 -> 6006.2276 | O41: =I41*Guide!K$167/I$56 -> 15094.113
A42: Include carbon credit flag | B42: =IF(Guide!G250="Included",1,0) -> 1 | E42: 12 | F42: 10176.308 | G42: 14246.831 | H42: 5945.4746 | I42: 15053.402 | K42: 12 | L42: =F42*Guide!H$167/F$56 -> 10181.733 | M42: =G42*Guide!I$167/G$56 -> 14251.686 | N42: =H42*Guide!J$167/H$56 -> 5941.3085 | O42: =I42*Guide!K$167/I$56 -> 14707.262
A43: Carbon price ($/t CO2e) | B43: =HLOOKUP(Guide!J245,Guide!$H$169:$J$170,2) -> 40 | E43: 13 | F43: 9787.9048 | G43: 13703.067 | H43: 5816.404 | I43: 14533.507 | K43: 13 | L43: =F43*Guide!H$167/F$56 -> 9793.123 | M43: =G43*Guide!I$167/G$56 -> 13707.736 | N43: =H43*Guide!J$167/H$56 -> 5812.3284 | O43: =I43*Guide!K$167/I$56 -> 14199.322
E44: 14 | F44: 9376.3499 | G44: 13126.89 | H44: 5645.3202 | I44: 13933.802 | K44: 14 | L44: =F44*Guide!H$167/F$56 -> 9381.3487 | M44: =G44*Guide!I$167/G$56 -> 13131.363 | N44: =H44*Guide!J$167/H$56 -> 5641.3645 | O44: =I44*Guide!K$167/I$56 -> 13613.406
B45: Central wheatbelt | C45: Eastern wheatbelt | E45: 15 | F45: 8957.8393 | G45: 12540.975 | H45: 5448.1397 | I45: -51931.896 | K45: 15 | L45: =F45*Guide!H$167/F$56 -> 8962.615 | M45: =G45*Guide!I$167/G$56 -> 12545.248 | N45: =H45*Guide!J$167/H$56 -> 5444.3221 | O45: =I45*Guide!K$167/I$56 -> -50737.768
A46: Regional growth scalar | B46: 1 | C46: 0.64 | E46: 16 | F46: 8542.8308 | G46: 11959.963 | H46: 5236.2255 | I46: 13459.407 | K46: 16 | L46: =F46*Guide!H$167/F$56 -> 8547.3853 | M46: =G46*Guide!I$167/G$56 -> 11964.039 | N46: =H46*Guide!J$167/H$56 -> 5232.5564 | O46: =I46*Guide!K$167/I$56 -> 13149.92
A47: LMU carbon scalar - poor soil | B47: 0.7 | C47: 0.845 | E47: 17 | F47: 8137.9502 | G47: 11393.13 | H47: 5017.6197 | I47: 13974.272 | K47: 17 | L47: =F47*Guide!H$167/F$56 -> 8142.2888 | M47: =G47*Guide!I$167/G$56 -> 11397.013 | N47: =H47*Guide!J$167/H$56 -> 5014.1038 | O47: =I47*Guide!K$167/I$56 -> 13652.946
A48: LMU carbon scalar - good soil | B48: 1 | C48: 1 | E48: 18 | F48: 7747.2518 | G48: 10846.153 | H48: 4797.9542 | I48: 14034.157 | K48: 18 | L48: =F48*Guide!H$167/F$56 -> 7751.3822 | M48: =G48*Guide!I$167/G$56 -> 10849.849 | N48: =H48*Guide!J$167/H$56 -> 4794.5922 | O48: =I48*Guide!K$167/I$56 -> 13711.454
A49: Regional growth scalar | B49: =HLOOKUP(Guide!$G$245,Calculations!$B$45:$C$46,2,FALSE) -> 1 | E49: 19 | F49: 7373.0618 | G49: 10322.287 | H49: 4581.1156 | I49: 13883.814 | K49: 19 | L49: =F49*Guide!H$167/F$56 -> 7376.9927 | M49: =G49*Guide!I$167/G$56 -> 10325.804 | N49: =H49*Guide!J$167/H$56 -> 4577.9055 | O49: =I49*Guide!K$167/I$56 -> 13564.568
A50: LMU carbon scalar | B50: =HLOOKUP(Guide!$G$245,$B$45:$C$48,IF(Guide!$G$247="Good",4,3),FALSE) -> 1 | E50: 20 | F50: 7016.546 | G50: 9823.1643 | H50: 4369.729 | I50: 13577.638 | K50: 20 | L50: =F50*Guide!H$167/F$56 -> 7020.2867 | M50: =G50*Guide!I$167/G$56 -> 9826.5117 | N50: =H50*Guide!J$167/H$56 -> 4366.6671 | O50: =I50*Guide!K$167/I$56 -> 13265.433
E51: 21 | F51: 6678.0962 | G51: 9349.3346 | H51: 4165.5091 | I51: -54805.162 | K51: 21 | L51: =F51*Guide!H$167/F$56 -> 6681.6565 | M51: =G51*Guide!I$167/G$56 -> 9352.5205 | N51: =H51*Guide!J$167/H$56 -> 4162.5903 | O51: =I51*Guide!K$167/I$56 -> -53544.967
E52: 22 | F52: 6357.5948 | G52: 8900.6328 | H52: 3969.5155 | I52: 13243.903 | K52: 22 | L52: =F52*Guide!H$167/F$56 -> 6360.9843 | M52: =G52*Guide!I$167/G$56 -> 8903.6658 | N52: =H52*Guide!J$167/H$56 -> 3966.7341 | O52: =I52*Guide!K$167/I$56 -> 12939.372
A53: PV of net cash flow | B53: =SUMPRODUCT(Calculations!M60:M85,Calculations!B60:B85) -> 2995.418 | E53: 23 | F53: 6054.5963 | G53: 8476.4348 | H53: 3782.3387 | I53: 13913.468 | K53: 23 | L53: =F53*Guide!H$167/F$56 -> 6057.8242 | M53: =G53*Guide!I$167/G$56 -> 8479.3233 | N53: =H53*Guide!J$167/H$56 -> 3779.6884 | O53: =I53*Guide!K$167/I$56 -> 13593.54
A54: Equivalent annual value ($/ha) | B54: =IF(Calculations!$B$41=0,B53/MAX(1,Calculations!$B$30),B53*(Calculations!$B$41/(1-(1+Calculations!$B$41)^-Calculations!$B$30))) -> 212.53227 | E54: 24 | F54: 5768.4514 | G54: 8075.8319 | H54: 3604.2352 | I54: 14087.081 | K54: 24 | L54: =F54*Guide!H$167/F$56 -> 5771.5267 | M54: =G54*Guide!I$167/G$56 -> 8078.5839 | N54: =H54*Guide!J$167/H$56 -> 3601.7097 | O54: =I54*Guide!K$167/I$56 -> 13763.161
E55: 25 | F55: 5498.3929 | G55: 7697.75 | H55: 3435.2265 | I55: -33731.607 | K55: 25 | L55: =F55*Guide!H$167/F$56 -> 5501.3242 | M55: =G55*Guide!I$167/G$56 -> 7700.3731 | N55: =H55*Guide!J$167/H$56 -> 3432.8194 | O55: =I55*Guide!K$167/I$56 -> -32955.979
F56: =AVERAGE(F31:F55)/1000 -> 7.4260409 | G56: =AVERAGE(G31:G55)/1000 -> 10.396457 | H56: =AVERAGE(H31:H55)/1000 -> 4.142903 | I56: =AVERAGE(I31:I55)/1000 -> 4.1350825 | L56: =AVERAGE(L31:L55)/1000 -> 7.43 | M56: =AVERAGE(M31:M55)/1000 -> 10.4 | N56: =AVERAGE(N31:N55)/1000 -> 4.14 | O56: =AVERAGE(O31:O55)/1000 -> 4.04
A58: Annual cashflow / emissions model
A59: Year | B59: Active | C59: Base seq. | D59: Adjusted seq. (kg/ha) | E59: Fuel used | F59: Fuel CO2e (kg/ha) | G59: Net CO2e (kg/ha) | H59: Income ($/ha) | I59: Variable costs ($/ha) | J59: Fixed costs | K59: Net cash flow | L59: Discount factor | M59: PV of net cash flow | N59: Notes
A60: 0 | B60: =--(A60<=Calculations!$B$30) -> 1 | C60: =INDEX(L30:O30,1,MATCH(Guide!$G$246,Scenarios!$B$2:$B$5,0)) -> 0 | D60: =C60*(1-Calculations!$B$29)*Calculations!$B$49*Calculations!$B$50 -> 0 | E60: =IF(B60=0,0,IF(A60=0,Calculations!$B$34,IF(A60=1,Calculations!$B$35,Calculations!$B$36))) -> 40 | F60: =E60*Calculations!$B$40 -> 108.62532 | G60: =D60-F60 -> -108.62532 | H60: =G60/1000*Calculations!$B$43*Calculations!$B$42 -> -4.3450128 | I60: =IF(AND(A60>=1,B60=1),Calculations!$B$32*Calculations!$B$42,0) -> 0 | J60: =IF(AND(A60=0,B60=1),Calculations!$B$33*Calculations!$B$42,0) -> 0 | K60: =H60-I60-J60 -> -4.3450128 | L60: =1/(1+Calculations!$B$41)^A60 -> 1 | M60: =K60*L60 -> -4.3450128 | N60: =IF(A60=0,"t0 / initial slice",IF(A60=1,"year 1","year 2+")) -> t0 / initial slice
A61: 1 | B61: =--(A61<=Calculations!$B$30) -> 1 | C61: =INDEX(L31:O31,1,MATCH(Guide!$G$246,Scenarios!$B$2:$B$5,0)) -> 645.13431 | D61: =C61*(1-Calculations!$B$29)*Calculations!$B$49*Calculations!$B$50 -> 612.87759 | E61: =IF(B61=0,0,IF(A61=0,Calculations!$B$34,IF(A61=1,Calculations!$B$35,Calculations!$B$36))) -> 8 | F61: =E61*Calculations!$B$40 -> 21.725064 | G61: =D61-F61 -> 591.15253 | H61: =G61/1000*Calculations!$B$43*Calculations!$B$42 -> 23.646101 | I61: =IF(AND(A61>=1,B61=1),Calculations!$B$32*Calculations!$B$42,0) -> 0 | J61: =IF(AND(A61=0,B61=1),Calculations!$B$33*Calculations!$B$42,0) -> 0 | K61: =H61-I61-J61 -> 23.646101 | L61: =1/(1+Calculations!$B$41)^A61 -> 0.95238095 | M61: =K61*L61 -> 22.520096 | N61: =IF(A61=0,"t0 / initial slice",IF(A61=1,"year 1","year 2+")) -> year 1
A62: 2 | B62: =--(A62<=Calculations!$B$30) -> 1 | C62: =INDEX(L32:O32,1,MATCH(Guide!$G$246,Scenarios!$B$2:$B$5,0)) -> 4333.4706 | D62: =C62*(1-Calculations!$B$29)*Calculations!$B$49*Calculations!$B$50 -> 4116.797 | E62: =IF(B62=0,0,IF(A62=0,Calculations!$B$34,IF(A62=1,Calculations!$B$35,Calculations!$B$36))) -> 0 | F62: =E62*Calculations!$B$40 -> 0 | G62: =D62-F62 -> 4116.797 | H62: =G62/1000*Calculations!$B$43*Calculations!$B$42 -> 164.67188 | I62: =IF(AND(A62>=1,B62=1),Calculations!$B$32*Calculations!$B$42,0) -> 0 | J62: =IF(AND(A62=0,B62=1),Calculations!$B$33*Calculations!$B$42,0) -> 0 | K62: =H62-I62-J62 -> 164.67188 | L62: =1/(1+Calculations!$B$41)^A62 -> 0.90702948 | M62: =K62*L62 -> 149.36225 | N62: =IF(A62=0,"t0 / initial slice",IF(A62=1,"year 1","year 2+")) -> year 2+
A63: 3 | B63: =--(A63<=Calculations!$B$30) -> 1 | C63: =INDEX(L33:O33,1,MATCH(Guide!$G$246,Scenarios!$B$2:$B$5,0)) -> 12753.614 | D63: =C63*(1-Calculations!$B$29)*Calculations!$B$49*Calculations!$B$50 -> 12115.934 | E63: =IF(B63=0,0,IF(A63=0,Calculations!$B$34,IF(A63=1,Calculations!$B$35,Calculations!$B$36))) -> 0 | F63: =E63*Calculations!$B$40 -> 0 | G63: =D63-F63 -> 12115.934 | H63: =G63/1000*Calculations!$B$43*Calculations!$B$42 -> 484.63735 | I63: =IF(AND(A63>=1,B63=1),Calculations!$B$32*Calculations!$B$42,0) -> 0 | J63: =IF(AND(A63=0,B63=1),Calculations!$B$33*Calculations!$B$42,0) -> 0 | K63: =H63-I63-J63 -> 484.63735 | L63: =1/(1+Calculations!$B$41)^A63 -> 0.8638376 | M63: =K63*L63 -> 418.64796 | N63: =IF(A63=0,"t0 / initial slice",IF(A63=1,"year 1","year 2+")) -> year 2+
A64: 4 | B64: =--(A64<=Calculations!$B$30) -> 1 | C64: =INDEX(L34:O34,1,MATCH(Guide!$G$246,Scenarios!$B$2:$B$5,0)) -> 17273.499 | D64: =C64*(1-Calculations!$B$29)*Calculations!$B$49*Calculations!$B$50 -> 16409.824 | E64: =IF(B64=0,0,IF(A64=0,Calculations!$B$34,IF(A64=1,Calculations!$B$35,Calculations!$B$36))) -> 0 | F64: =E64*Calculations!$B$40 -> 0 | G64: =D64-F64 -> 16409.824 | H64: =G64/1000*Calculations!$B$43*Calculations!$B$42 -> 656.39296 | I64: =IF(AND(A64>=1,B64=1),Calculations!$B$32*Calculations!$B$42,0) -> 0 | J64: =IF(AND(A64=0,B64=1),Calculations!$B$33*Calculations!$B$42,0) -> 0 | K64: =H64-I64-J64 -> 656.39296 | L64: =1/(1+Calculations!$B$41)^A64 -> 0.82270247 | M64: =K64*L64 -> 540.01611 | N64: =IF(A64=0,"t0 / initial slice",IF(A64=1,"year 1","year 2+")) -> year 2+
A65: 5 | B65: =--(A65<=Calculations!$B$30) -> 1 | C65: =INDEX(L35:O35,1,MATCH(Guide!$G$246,Scenarios!$B$2:$B$5,0)) -> 18321.412 | D65: =C65*(1-Calculations!$B$29)*Calculations!$B$49*Calculations!$B$50 -> 17405.342 | E65: =IF(B65=0,0,IF(A65=0,Calculations!$B$34,IF(A65=1,Calculations!$B$35,Calculations!$B$36))) -> 0 | F65: =E65*Calculations!$B$40 -> 0 | G65: =D65-F65 -> 17405.342 | H65: =G65/1000*Calculations!$B$43*Calculations!$B$42 -> 696.21367 | I65: =IF(AND(A65>=1,B65=1),Calculations!$B$32*Calculations!$B$42,0) -> 0 | J65: =IF(AND(A65=0,B65=1),Calculations!$B$33*Calculations!$B$42,0) -> 0 | K65: =H65-I65-J65 -> 696.21367 | L65: =1/(1+Calculations!$B$41)^A65 -> 0.78352617 | M65: =K65*L65 -> 545.50163 | N65: =IF(A65=0,"t0 / initial slice",IF(A65=1,"year 1","year 2+")) -> year 2+
A66: 6 | B66: =--(A66<=Calculations!$B$30) -> 1 | C66: =INDEX(L36:O36,1,MATCH(Guide!$G$246,Scenarios!$B$2:$B$5,0)) -> 17779.895 | D66: =C66*(1-Calculations!$B$29)*Calculations!$B$49*Calculations!$B$50 -> 16890.9 | E66: =IF(B66=0,0,IF(A66=0,Calculations!$B$34,IF(A66=1,Calculations!$B$35,Calculations!$B$36))) -> 0 | F66: =E66*Calculations!$B$40 -> 0 | G66: =D66-F66 -> 16890.9 | H66: =G66/1000*Calculations!$B$43*Calculations!$B$42 -> 675.63601 | I66: =IF(AND(A66>=1,B66=1),Calculations!$B$32*Calculations!$B$42,0) -> 0 | J66: =IF(AND(A66=0,B66=1),Calculations!$B$33*Calculations!$B$42,0) -> 0 | K66: =H66-I66-J66 -> 675.63601 | L66: =1/(1+Calculations!$B$41)^A66 -> 0.7462154 | M66: =K66*L66 -> 504.16999 | N66: =IF(A66=0,"t0 / initial slice",IF(A66=1,"year 1","year 2+")) -> year 2+
A67: 7 | B67: =--(A67<=Calculations!$B$30) -> 1 | C67: =INDEX(L37:O37,1,MATCH(Guide!$G$246,Scenarios!$B$2:$B$5,0)) -> 16651.878 | D67: =C67*(1-Calculations!$B$29)*Calculations!$B$49*Calculations!$B$50 -> 15819.284 | E67: =IF(B67=0,0,IF(A67=0,Calculations!$B$34,IF(A67=1,Calculations!$B$35,Calculations!$B$36))) -> 0 | F67: =E67*Calculations!$B$40 -> 0 | G67: =D67-F67 -> 15819.284 | H67: =G67/1000*Calculations!$B$43*Calculations!$B$42 -> 632.77138 | I67: =IF(AND(A67>=1,B67=1),Calculations!$B$32*Calculations!$B$42,0) -> 0 | J67: =IF(AND(A67=0,B67=1),Calculations!$B$33*Calculations!$B$42,0) -> 0 | K67: =H67-I67-J67 -> 632.77138 | L67: =1/(1+Calculations!$B$41)^A67 -> 0.71068133 | M67: =K67*L67 -> 449.6988 | N67: =IF(A67=0,"t0 / initial slice",IF(A67=1,"year 1","year 2+")) -> year 2+
A68: 8 | B68: =--(A68<=Calculations!$B$30) -> 1 | C68: =INDEX(L38:O38,1,MATCH(Guide!$G$246,Scenarios!$B$2:$B$5,0)) -> 15365.611 | D68: =C68*(1-Calculations!$B$29)*Calculations!$B$49*Calculations!$B$50 -> 14597.33 | E68: =IF(B68=0,0,IF(A68=0,Calculations!$B$34,IF(A68=1,Calculations!$B$35,Calculations!$B$36))) -> 0 | F68: =E68*Calculations!$B$40 -> 0 | G68: =D68-F68 -> 14597.33 | H68: =G68/1000*Calculations!$B$43*Calculations!$B$42 -> 583.89321 | I68: =IF(AND(A68>=1,B68=1),Calculations!$B$32*Calculations!$B$42,0) -> 0 | J68: =IF(AND(A68=0,B68=1),Calculations!$B$33*Calculations!$B$42,0) -> 0 | K68: =H68-I68-J68 -> 583.89321 | L68: =1/(1+Calculations!$B$41)^A68 -> 0.67683936 | M68: =K68*L68 -> 395.20191 | N68: =IF(A68=0,"t0 / initial slice",IF(A68=1,"year 1","year 2+")) -> year 2+
A69: 9 | B69: =--(A69<=Calculations!$B$30) -> 1 | C69: =INDEX(L39:O39,1,MATCH(Guide!$G$246,Scenarios!$B$2:$B$5,0)) -> -45264.891 | D69: =C69*(1-Calculations!$B$29)*Calculations!$B$49*Calculations!$B$50 -> -43001.647 | E69: =IF(B69=0,0,IF(A69=0,Calculations!$B$34,IF(A69=1,Calculations!$B$35,Calculations!$B$36))) -> 0 | F69: =E69*Calculations!$B$40 -> 0 | G69: =D69-F69 -> -43001.647 | H69: =G69/1000*Calculations!$B$43*Calculations!$B$42 -> -1720.0659 | I69: =IF(AND(A69>=1,B69=1),Calculations!$B$32*Calculations!$B$42,0) -> 0 | J69: =IF(AND(A69=0,B69=1),Calculations!$B$33*Calculations!$B$42,0) -> 0 | K69: =H69-I69-J69 -> -1720.0659 | L69: =1/(1+Calculations!$B$41)^A69 -> 0.64460892 | M69: =K69*L69 -> -1108.7698 | N69: =IF(A69=0,"t0 / initial slice",IF(A69=1,"year 1","year 2+")) -> year 2+
A70: 10 | B70: =--(A70<=Calculations!$B$30) -> 1 | C70: =INDEX(L40:O40,1,MATCH(Guide!$G$246,Scenarios!$B$2:$B$5,0)) -> 15124.593 | D70: =C70*(1-Calculations!$B$29)*Calculations!$B$49*Calculations!$B$50 -> 14368.364 | E70: =IF(B70=0,0,IF(A70=0,Calculations!$B$34,IF(A70=1,Calculations!$B$35,Calculations!$B$36))) -> 0 | F70: =E70*Calculations!$B$40 -> 0 | G70: =D70-F70 -> 14368.364 | H70: =G70/1000*Calculations!$B$43*Calculations!$B$42 -> 574.73454 | I70: =IF(AND(A70>=1,B70=1),Calculations!$B$32*Calculations!$B$42,0) -> 0 | J70: =IF(AND(A70=0,B70=1),Calculations!$B$33*Calculations!$B$42,0) -> 0 | K70: =H70-I70-J70 -> 574.73454 | L70: =1/(1+Calculations!$B$41)^A70 -> 0.61391325 | M70: =K70*L70 -> 352.83715 | N70: =IF(A70=0,"t0 / initial slice",IF(A70=1,"year 1","year 2+")) -> year 2+
A71: 11 | B71: =--(A71<=Calculations!$B$30) -> 1 | C71: =INDEX(L41:O41,1,MATCH(Guide!$G$246,Scenarios!$B$2:$B$5,0)) -> 15094.113 | D71: =C71*(1-Calculations!$B$29)*Calculations!$B$49*Calculations!$B$50 -> 14339.408 | E71: =IF(B71=0,0,IF(A71=0,Calculations!$B$34,IF(A71=1,Calculations!$B$35,Calculations!$B$36))) -> 0 | F71: =E71*Calculations!$B$40 -> 0 | G71: =D71-F71 -> 14339.408 | H71: =G71/1000*Calculations!$B$43*Calculations!$B$42 -> 573.5763 | I71: =IF(AND(A71>=1,B71=1),Calculations!$B$32*Calculations!$B$42,0) -> 0 | J71: =IF(AND(A71=0,B71=1),Calculations!$B$33*Calculations!$B$42,0) -> 0 | K71: =H71-I71-J71 -> 573.5763 | L71: =1/(1+Calculations!$B$41)^A71 -> 0.58467929 | M71: =K71*L71 -> 335.35819 | N71: =IF(A71=0,"t0 / initial slice",IF(A71=1,"year 1","year 2+")) -> year 2+
... A85: 25 | B85: =--(A85<=Calculations!$B$30) -> 1 | C85: =INDEX(L55:O55,1,MATCH(Guide!$G$246,Scenarios!$B$2:$B$5,0)) -> -32955.979 | D85: =C85*(1-Calculations!$B$29)*Calculations!$B$49*Calculations!$B$50 -> -31308.18 | E85: =IF(B85=0,0,IF(A85=0,Calculations!$B$34,IF(A85=1,Calculations!$B$35,Calculations!$B$36))) -> 0 | F85: =E85*Calculations!$B$40 -> 0 | G85: =D85-F85 -> -31308.18 | H85: =G85/1000*Calculations!$B$43*Calculations!$B$42 -> -1252.3272 | I85: =IF(AND(A85>=1,B85=1),Calculations!$B$32*Calculations!$B$42,0) -> 0 | J85: =IF(AND(A85=0,B85=1),Calculations!$B$33*Calculations!$B$42,0) -> 0 | K85: =H85-I85-J85 -> -1252.3272 | L85: =1/(1+Calculations!$B$41)^A85 -> 0.29530277 | M85: =K85*L85 -> -369.81569 | N85: =IF(A85=0,"t0 / initial slice",IF(A85=1,"year 1","year 2+")) -> year 2+
A109: Biodiversity
A111: Discount rate | B111: =B12 -> 0.05
A112: Project length | B112: =B13 -> 25
A113: Biodiversity value | B113: =HLOOKUP(Guide!$G$246,Guide!$H$194:$K$195,2,FALSE)*HLOOKUP(Guide!$J$246,Scenarios!A10:$C$11,2,FALSE) -> 4500
A114: Annual monitoring cost | B114: =Guide!H116 -> 25
A115: Fixed set up cost ($/ha) | B115: =Guide!H115/Guide!G248 -> 10000
A117: Income (all at time 0 → NOT discounted) | B117: =B113 -> 4500
A118: Fixed cost (time 0 → NOT discounted) | B118: =B115 -> 10000
A119: Variable costs (years 1 → n) | B119: {=SUMPRODUCT(B114/(1+$B$111)^(ROW(INDIRECT("1:"&$B$112))))} -> 352.34861
A121: Income (perpetual) | B121: =B113 * ($B$111 / (1 - (1+$B$111)^-$B$112)) -> 319.28606
A122: Annual variable cost | B122: =B119 * ($B$111 / (1 - (1+$B$111)^-$B$112)) -> 25
A123: Annual fixed cost | B123: =B118 * ($B$111 / (1 - (1+$B$111)^-$B$112)) -> 709.52457
B124: =IF(Guide!$G$251="Included",B121-B122-B123,0) -> -415.23852
A128: Biomass
A129: Project duration (years) | B129: 25 | E129: Year | F129: ='[2]Planting config'!$G$13 -> Carbon | G129: ='[2]Planting config'!$H$13 -> Carbon & co-benefits | H129: ='[2]Planting config'!$I$13 -> Biodiversity | I129: ='[2]Planting config'!$J$13 -> Harvested | K129: Year | L129: ='[2]Planting config'!$G$13 -> Carbon | M129: ='[2]Planting config'!$H$13 -> Carbon & co-benefits | N129: ='[2]Planting config'!$I$13 -> Biodiversity | O129: ='[2]Planting config'!$J$13 -> Harvested
A130: Discount rate | B130: =$B$12 -> 0.05 | E130: 0 | F130: 0 | G130: 0 | H130: 0 | I130: 0 | K130: 0 | L130: =IFERROR(F130*Guide!H$201/F$156,0) -> 0 | M130: =IFERROR(G130*Guide!I$201/G$156,0) -> 0 | N130: =IFERROR(H130*Guide!J$201/H$156,0) -> 0 | O130: =IFERROR(I130*Guide!K$201/I$156,0) -> 0
A131: Harvested? (TRUE/FALSE) | B131: =IF(Guide!$G$252="Included",TRUE,FALSE) -> TRUE | E131: 1 | F131: 0 | G131: 0 | H131: 0 | I131: 0 | K131: 1 | L131: =IFERROR(F131*Guide!H$201/F$156,0) -> 0 | M131: =IFERROR(G131*Guide!I$201/G$156,0) -> 0 | N131: =IFERROR(H131*Guide!J$201/H$156,0) -> 0 | O131: =IFERROR(I131*Guide!K$201/I$156,0) -> 0
E132: 2 | F132: 0 | G132: 0 | H132: 0 | I132: 0 | K132: 2 | L132: =IFERROR(F132*Guide!H$201/F$156,0) -> 0 | M132: =IFERROR(G132*Guide!I$201/G$156,0) -> 0 | N132: =IFERROR(H132*Guide!J$201/H$156,0) -> 0 | O132: =IFERROR(I132*Guide!K$201/I$156,0) -> 0
A133: Biomass price ($/t) | B133: =HLOOKUP(Guide!$J$247,Guide!$H$203:$J$204,2,FALSE) -> 50 | E133: 3 | F133: 0 | G133: 0 | H133: 0 | I133: 0 | K133: 3 | L133: =IFERROR(F133*Guide!H$201/F$156,0) -> 0 | M133: =IFERROR(G133*Guide!I$201/G$156,0) -> 0 | N133: =IFERROR(H133*Guide!J$201/H$156,0) -> 0 | O133: =IFERROR(I133*Guide!K$201/I$156,0) -> 0
A134: Contract costs ($/hr) | B134: =Guide!H117 -> 300 | E134: 4 | F134: 0 | G134: 0 | H134: 0 | I134: 0 | K134: 4 | L134: =IFERROR(F134*Guide!H$201/F$156,0) -> 0 | M134: =IFERROR(G134*Guide!I$201/G$156,0) -> 0 | N134: =IFERROR(H134*Guide!J$201/H$156,0) -> 0 | O134: =IFERROR(I134*Guide!K$201/I$156,0) -> 0
A135: Harvest rate (t/hr) | B135: =Guide!H118 -> 40 | E135: 5 | F135: 0 | G135: 0 | H135: 0 | I135: 0 | K135: 5 | L135: =IFERROR(F135*Guide!H$201/F$156,0) -> 0 | M135: =IFERROR(G135*Guide!I$201/G$156,0) -> 0 | N135: =IFERROR(H135*Guide!J$201/H$156,0) -> 0 | O135: =IFERROR(I135*Guide!K$201/I$156,0) -> 0
A136: Transport cost ($/t/km) | B136: =Guide!H119 -> 0.15 | E136: 6 | F136: 0 | G136: 0 | H136: 0 | I136: 0 | K136: 6 | L136: =IFERROR(F136*Guide!H$201/F$156,0) -> 0 | M136: =IFERROR(G136*Guide!I$201/G$156,0) -> 0 | N136: =IFERROR(H136*Guide!J$201/H$156,0) -> 0 | O136: =IFERROR(I136*Guide!K$201/I$156,0) -> 0
A137: Transport distance (km) | B137: =Guide!H120 -> 60 | E137: 7 | F137: 0 | G137: 0 | H137: 0 | I137: 0 | K137: 7 | L137: =IFERROR(F137*Guide!H$201/F$156,0) -> 0 | M137: =IFERROR(G137*Guide!I$201/G$156,0) -> 0 | N137: =IFERROR(H137*Guide!J$201/H$156,0) -> 0 | O137: =IFERROR(I137*Guide!K$201/I$156,0) -> 0
A138: Cost per tonne | B138: =($B$134/$B$135)+($B$136*$B$137) -> 16.5 | E138: 8 | F138: 0 | G138: 0 | H138: 0 | I138: =27.5214412463052/0.65 -> 42.340679 | K138: 8 | L138: =IFERROR(F138*Guide!H$201/F$156,0) -> 0 | M138: =IFERROR(G138*Guide!I$201/G$156,0) -> 0 | N138: =IFERROR(H138*Guide!J$201/H$156,0) -> 0 | O138: =IFERROR(I138*Guide!K$201/I$156,0) -> 42.340679
E139: 9 | F139: 0 | G139: 0 | H139: 0 | I139: 0 | K139: 9 | L139: =IFERROR(F139*Guide!H$201/F$156,0) -> 0 | M139: =IFERROR(G139*Guide!I$201/G$156,0) -> 0 | N139: =IFERROR(H139*Guide!J$201/H$156,0) -> 0 | O139: =IFERROR(I139*Guide!K$201/I$156,0) -> 0
B140: Central wheatbelt | C140: Eastern wheatbelt | E140: 10 | F140: 0 | G140: 0 | H140: 0 | I140: 0 | K140: 10 | L140: =IFERROR(F140*Guide!H$201/F$156,0) -> 0 | M140: =IFERROR(G140*Guide!I$201/G$156,0) -> 0 | N140: =IFERROR(H140*Guide!J$201/H$156,0) -> 0 | O140: =IFERROR(I140*Guide!K$201/I$156,0) -> 0
A141: Regional growth scalar | B141: 1 | C141: 0.64 | E141: 11 | F141: 0 | G141: 0 | H141: 0 | I141: 0 | K141: 11 | L141: =IFERROR(F141*Guide!H$201/F$156,0) -> 0 | M141: =IFERROR(G141*Guide!I$201/G$156,0) -> 0 | N141: =IFERROR(H141*Guide!J$201/H$156,0) -> 0 | O141: =IFERROR(I141*Guide!K$201/I$156,0) -> 0
A142: LMU growth scalar - poor soil | B142: 0.39 | C142: 0.69 | E142: 12 | F142: 0 | G142: 0 | H142: 0 | I142: 0 | K142: 12 | L142: =IFERROR(F142*Guide!H$201/F$156,0) -> 0 | M142: =IFERROR(G142*Guide!I$201/G$156,0) -> 0 | N142: =IFERROR(H142*Guide!J$201/H$156,0) -> 0 | O142: =IFERROR(I142*Guide!K$201/I$156,0) -> 0
A143: LMU growth scalar - good soil | B143: 1 | C143: 1 | E143: 13 | F143: 0 | G143: 0 | H143: 0 | I143: 0 | K143: 13 | L143: =IFERROR(F143*Guide!H$201/F$156,0) -> 0 | M143: =IFERROR(G143*Guide!I$201/G$156,0) -> 0 | N143: =IFERROR(H143*Guide!J$201/H$156,0) -> 0 | O143: =IFERROR(I143*Guide!K$201/I$156,0) -> 0
A144: Regional growth scalar | B144: =HLOOKUP(Guide!$G$245,$B$140:$C$141,2,FALSE) -> 1 | E144: 14 | F144: 0 | G144: 0 | H144: 0 | I144: =28.9432214433091/0.65 -> 44.528033 | K144: 14 | L144: =IFERROR(F144*Guide!H$201/F$156,0) -> 0 | M144: =IFERROR(G144*Guide!I$201/G$156,0) -> 0 | N144: =IFERROR(H144*Guide!J$201/H$156,0) -> 0 | O144: =IFERROR(I144*Guide!K$201/I$156,0) -> 44.528033
A145: LMU growth scalar | B145: =HLOOKUP(Guide!$G$245,$B$140:$C$143,IF(Guide!$G$247="Good",4,3),FALSE) -> 1 | E145: 15 | F145: 0 | G145: 0 | H145: 0 | I145: 0 | K145: 15 | L145: =IFERROR(F145*Guide!H$201/F$156,0) -> 0 | M145: =IFERROR(G145*Guide!I$201/G$156,0) -> 0 | N145: =IFERROR(H145*Guide!J$201/H$156,0) -> 0 | O145: =IFERROR(I145*Guide!K$201/I$156,0) -> 0
E146: 16 | F146: 0 | G146: 0 | H146: 0 | I146: 0 | K146: 16 | L146: =IFERROR(F146*Guide!H$201/F$156,0) -> 0 | M146: =IFERROR(G146*Guide!I$201/G$156,0) -> 0 | N146: =IFERROR(H146*Guide!J$201/H$156,0) -> 0 | O146: =IFERROR(I146*Guide!K$201/I$156,0) -> 0
E147: 17 | F147: 0 | G147: 0 | H147: 0 | I147: 0 | K147: 17 | L147: =IFERROR(F147*Guide!H$201/F$156,0) -> 0 | M147: =IFERROR(G147*Guide!I$201/G$156,0) -> 0 | N147: =IFERROR(H147*Guide!J$201/H$156,0) -> 0 | O147: =IFERROR(I147*Guide!K$201/I$156,0) -> 0
...

Sheet Scenarios
A1: Location | B1: Scenario | C1: Soil | D1: Planting Area (ha) | E1: Carbon credit price | F1: Biodiversity credit price | G1: Biomass price | H1: Components | I1: Micro-climate benefit | J1: Erosion Benefits | K1: Rate of salinity spread
A2: Central wheatbelt | B2: Carb Block | C2: Poor | D2: 1 | E2: Low (-50%) | F2: Low -50% | G2: Low -50% | H2: nil | I2: nil | J2: nil | K2: nil
A3: Eastern wheatbelt | B3: Carb Belt | C3: Good | D3: 10 | E3: Standard | F3: Standard | G3: Standard | H3: Included | I3: Included | J3: Increased summer grazing +500kg/ha | K3: 0.0089
B4: Bio Block | D4: 100 | E4: High (+50%) | F4: Low +50% | G4: Low +50%
B5: Harv Belt
A10: Low -50% | B10: Standard | C10: Low +50%
A11: 0.5 | B11: 1 | C11: 1.5
